rtl/bram.v
//============================================================================
//
//  This program is free software; you can redistribute it and/or modify it
//  under the terms of the GNU General Public License as published by the Free
//  Software Foundation; either version 2 of the License, or (at your option)
//  any later version.
//
//  This program is distributed in the hope that it will be useful, but WITHOUT
//  ANY WARRANTY; without even the implied warranty of MERCHANTABILITY or
//  FITNESS FOR A PARTICULAR PURPOSE.  See the GNU General Public License for
//  more details.
//
//  You should have received a copy of the GNU General Public License along
//  with this program; if not, write to the Free Software Foundation, Inc.,
//  51 Franklin Street, Fifth Floor, Boston, MA 02110-1301 USA.
//
//============================================================================

//`timescale 1ns / 1ps

module bram 
#
(
	parameter DW = 8,
	parameter AW = 12
)
(
  
  input            clk,

  input            bram_download,
  input            bram_wr,
  input     [24:0] bram_init_address,
  input      [7:0] bram_din,

  input            cs,
  input     [24:0] addr,
  output reg [7:0] dout
);

reg[DW-1:0] memory[(2**AW)-1:0];

always @(posedge clk) begin
  if (bram_download && bram_wr) begin
    //$display("bram_din %x bram_init_address %x", bram_din, bram_init_address);
    memory[bram_init_address] <= bram_din;
  end
  else if (cs)
    dout <= memory[addr];
end

endmodule

rtl/rom.v
//============================================================================
//
//  This program is free software; you can redistribute it and/or modify it
//  under the terms of the GNU General Public License as published by the Free
//  Software Foundation; either version 2 of the License, or (at your option)
//  any later version.
//
//  This program is distributed in the hope that it will be useful, but WITHOUT
//  ANY WARRANTY; without even the implied warranty of MERCHANTABILITY or
//  FITNESS FOR A PARTICULAR PURPOSE.  See the GNU General Public License for
//  more details.
//
//  You should have received a copy of the GNU General Public License along
//  with this program; if not, write to the Free Software Foundation, Inc.,
//  51 Franklin Street, Fifth Floor, Boston, MA 02110-1301 USA.
//
//============================================================================

//-------------------------------------------------------------------------------------------------
module rom
//-------------------------------------------------------------------------------------------------
#
(
	parameter DW = 8,
	parameter AW = 14,
	parameter FN = ""
)
(
	input  wire         clock,
	input  wire         ce,
	output reg [DW-1:0] data_out,
	input  wire[AW-1:0] a
);
//-------------------------------------------------------------------------------------------------

reg[DW-1:0] d[(2**AW)-1:0];

if(FN) initial $readmemh(FN, d, 0);

always @(posedge clock) if(ce) data_out<= d[a];

//-------------------------------------------------------------------------------------------------
endmodule
//-------------------------------------------------------------------------------------------------

rtl/cdp1802.v
//============================================================================
//
//  This program is free software; you can redistribute it and/or modify it
//  under the terms of the GNU General Public License as published by the Free
//  Software Foundation; either version 2 of the License, or (at your option)
//  any later version.
//
//  This program is distributed in the hope that it will be useful, but WITHOUT
//  ANY WARRANTY; without even the implied warranty of MERCHANTABILITY or
//  FITNESS FOR A PARTICULAR PURPOSE.  See the GNU General Public License for
//  more details.
//
//  You should have received a copy of the GNU General Public License along
//  with this program; if not, write to the Free Software Foundation, Inc.,
//  51 Franklin Street, Fifth Floor, Boston, MA 02110-1301 USA.
//
//============================================================================

`default_nettype none
/* verilator lint_off UNOPTFLAT */

module cdp1802 (
  input               clock,
  input               resetq,

  output reg          Q,          // external pin Q
  input      [3:0]    EF,         // external flags EF1 to EF4

  input      [7:0]    io_din,     // IO data in
  output     [7:0]    io_dout,    // IO data out
  output     [2:0]    io_n,       // IO control lines: N2,N1,N0
  output  wire        io_inp,     // IO input signal
  output  wire        io_out,     // IO output signal

  output              unsupported,// unsupported instruction signal

  output              ram_rd,     // RAM read enable
  output              ram_wr,     // RAM write enable
  output     [15:0]   ram_a,      // RAM address
  input      [7:0]    ram_q,      // RAM read data
  output     [7:0]    ram_d       // RAM write data
);

  // ---------- execution states -------------------------
  reg [2:0] state, state_n;

  localparam RESET     = 3'd0;    // hardware reset asserted
  localparam FETCH     = 3'd1;    // fetching opcode from PC
  localparam EXECUTE   = 3'd2;    // main exection state
  localparam EXECUTE2  = 3'd3;    // second execute, if memory was read
  localparam BRANCH2   = 3'd4;    // long branch, collect new PC hi-byte
  localparam BRANCH3   = 3'd5;    // short branch, new PC lo-byte
  localparam SKIP      = 3'd6;    // for untaken branch

  // ---------- registers --------------------------------
  reg [3:0] P, X;

  reg [15:0] R[0:15];             // 16x16 register file
  wire [3:0] Ra;                  // which register to work on this clock
  wire [15:0] Rrd = R[Ra];        // read out the selected register
  reg [15:0] Rwd;                 // write-back value for the register

  reg [7:0] D;                    // data register (accumulator)
  reg DF;                         // data flag (ALU carry)
  reg [7:0] B;                    // used for hi-byte of long branch
  reg [7:0] ram_q_;               // registered copy of ram_q, for multi-cycle ops
  wire [3:0] I, N;                // the current instruction

  // ---------- RAM hookups ------------------------------
  assign ram_d = (I == 4'h6) ? io_din : D;
  assign ram_a = Rrd;             // RAM address always one of the 16-bit regs

  // ---------- conditional branch -----------------------
  reg sense;
  always @*
    casez ({I, N})
      {4'h3, 4'b?000}, {4'hc, 4'b??00}: sense = 1;
      {4'h3, 4'b?001}, {4'hc, 4'b??01}: sense = Q;
      {4'h3, 4'b?010}, {4'hc, 4'b??10}: sense = (D == 8'h00);
      {4'h3, 4'b?011}, {4'hc, 4'b??11}: sense = DF;
      {4'h3, 4'b?1??}:                  sense = EF[N[1:0]];
      default:                          sense = 1'bx;
    endcase
  wire take = sense ^ N[3];

  // ---------- fetch/execute ----------------------------
  always @*
    case (state)
    FETCH:      state_n = EXECUTE;
    EXECUTE:
      case (I)
      4'h3:     state_n = take ? BRANCH3 : FETCH;
      4'hc:     state_n = take ? BRANCH2 : SKIP;
      default:  state_n = ram_rd ? EXECUTE2 : FETCH;
      endcase
    BRANCH2:    state_n = BRANCH3;
    default:    state_n = FETCH;
    endcase
  assign {I, N} = (state == EXECUTE) ? ram_q : ram_q_;

  // ---------- decode and execute -----------------------
  wire [3:0] P_n = ((I == 4'hD)) ? N : P;           // SEP
  wire [3:0] X_n = ((I == 4'hE)) ? N : X;           // SEX
  wire Q_n = (({I, N} == 8'h7a) | ({I, N} == 8'h7b)) ? N[0] : Q; // REQ, SEQ

  reg [5:0] action;                 // reg. address; RAM rd; RAM wr
  assign {Ra, ram_rd, ram_wr} = action;

  localparam MEM___  = 2'b00;       // no memory access
  localparam MEM_RD  = 2'b10;       // memory read strobe
  localparam MEM_WR  = 2'b01;       // memory write strobe

  always @(state, I, N)
    case (state)
    FETCH, BRANCH2, SKIP:           {action, Rwd} = {P, MEM_RD, Rrd + 16'd1};
    EXECUTE, EXECUTE2:
      casez ({I, N})
      /* LDN  */ 8'h0?:             {action, Rwd} = {N, MEM_RD, Rrd};
      /* INC  */ 8'h1?:             {action, Rwd} = {N, MEM___, Rrd + 16'd1};
      /* DEC  */ 8'h2?:             {action, Rwd} = {N, MEM___, Rrd - 16'd1};
      /* LDA  */ 8'h4?:             {action, Rwd} = {N, MEM_RD, Rrd + 16'd1};
      /* STR  */ 8'h5?:             {action, Rwd} = {N, MEM_WR, Rrd};
      /* SEP  */ 8'hd?,
      /* SEX  */ 8'he?,
      /* GLO  */ 8'h8?,
      /* GHI  */ 8'h9?:             {action, Rwd} = {N, MEM___, Rrd};
      /* PLO  */ 8'ha?:             {action, Rwd} = {N, MEM___, Rrd[15:8], D};
      /* PHI  */ 8'hb?:             {action, Rwd} = {N, MEM___, D, Rrd[7:0]};

      /* STXD */ 8'h73:             {action, Rwd} = {X, MEM_WR, Rrd - 16'd1};
      /* LDXA */ 8'h72,
      /* OUT  */ {4'h6, 4'b0???}:   {action, Rwd} = {X, MEM_RD, Rrd + 16'd1};
      /* INP  */ {4'h6, 4'b1???}:   {action, Rwd} = {X, MEM_WR, Rrd};

      /* immediate and branch instructions must fetch from R[P] */
      8'h7c, 8'h7d, 8'h7f, 8'hf8, 8'hf9, 8'hfa, 8'hfb, 8'hfc, 8'hfd, 8'hff,
      8'h3?, 8'hc?:                 {action, Rwd} = {P, MEM_RD, Rrd + 16'd1};

      default:                      {action, Rwd} = {X, MEM_RD, Rrd};
      endcase
    BRANCH3:                        {action, Rwd} = {P, MEM___, (I == 4'hc) ? B : Rrd[15:8], ram_q};
    default:                        {action, Rwd} = {X, MEM___, Rrd};
    endcase

  wire [8:0] carry = (I[3]) ? 9'd0 : {8'd0, DF};      // 0 or 1 for ADC
  wire [8:0] borrow = (I[3]) ? 9'd0 : ~{9{DF}};       // -1 or 0 for SDB and SMB
  reg [8:0] DFD_n;
  always @*
    casez ({I, N})
    /* LDXA */ 8'h72,
    /* LDX  */ 8'hf0,
    /* LDI  */ 8'hf8,
    /* LDA  */ 8'h4?,
    /* LDN  */ 8'h0?:               DFD_n = {DF, ram_q};
    /* GLO  */ 8'h8?:               DFD_n = {DF, Rrd[7:0]};
    /* GHI  */ 8'h9?:               DFD_n = {DF, Rrd[15:8]};
    /* INP  */ 8'b0110_1???:        DFD_n = {DF, io_din};
    /* OR   */ 8'b1111_?001:        DFD_n = {DF, D | ram_q};
    /* AND  */ 8'b1111_?010:        DFD_n = {DF, D & ram_q};
    /* XOR  */ 8'b1111_?011:        DFD_n = {DF, D ^ ram_q};
    /* ADD  */ 8'b?111_?100:        DFD_n = {1'b0, D} + {1'b0, ram_q} + carry;
    /* SD   */ 8'b?111_?101:        DFD_n = ({1'b1, ram_q} - {1'b0, D}) + borrow;
    /* SM   */ 8'b?111_?111:        DFD_n = ({1'b1, D} - {1'b0, ram_q}) + borrow;
    /* SHR  */ 8'b?111_0110:        DFD_n = {D[0], carry[0], D[7:1]};
    /* SHL  */ 8'b?111_1110:        DFD_n = {D, carry[0]};
    default:                        DFD_n = {DF, D};
    endcase

  assign io_n = N[2:0];
  assign io_out = (I == 4'h6) & ~N[3] & (state == EXECUTE2) & (N[2:0] != 3'b000);
  assign io_inp = (I == 4'h6) & N[3] & (state == EXECUTE) & (N[2:0] != 3'b000);
  assign io_dout = ram_q;
  assign unsupported = {I, N} == 8'h70;

  // ---------- cycle commit -----------------------------
  always @(negedge resetq or posedge clock)
    if (!resetq) begin
      {ram_q_, Q, P, X} <= 0;
      {DF, D} <= 9'd0;
      R[0] <= 16'd0;
      state <= RESET;
    end else begin
      state <= state_n;
      if (state == EXECUTE)
        {ram_q_, Q, P, X} <= {ram_q, Q_n, P_n, X_n};
      if (state != EXECUTE2)
        R[Ra] <= Rwd;
      if (((state == EXECUTE) & !ram_rd) || (state == EXECUTE2))
        {DF, D} <= DFD_n;
      if (state == BRANCH2)
        B <= ram_q;
    end

endmodule

rtl/cdp1861.v
//============================================================================
//
//  This program is free software; you can redistribute it and/or modify it
//  under the terms of the GNU General Public License as published by the Free
//  Software Foundation; either version 2 of the License, or (at your option)
//  any later version.
//
//  This program is distributed in the hope that it will be useful, but WITHOUT
//  ANY WARRANTY; without even the implied warranty of MERCHANTABILITY or
//  FITNESS FOR A PARTICULAR PURPOSE.  See the GNU General Public License for
//  more details.
//
//  You should have received a copy of the GNU General Public License along
//  with this program; if not, write to the Free Software Foundation, Inc.,
//  51 Franklin Street, Fifth Floor, Boston, MA 02110-1301 USA.
//
//============================================================================

module cdp1861 (

    input               clock,
    input               reset,

    input               Disp_On,
    input               Disp_Off,
    input               TPA,
    input               TPB,
    input       [1:0]   SC,
    input       [7:0]   DataIn,

    output              Clear,
    output reg          INT,
    output reg          DMAO,
    output reg          EFx,

    output reg          video,
    output reg          CompSync,
    output              Locked
);

//Line and Machine Cycle counter
reg lineCounter;   // max 'd263;
reg MCycleCounter; // max 'd28;
reg syncCounter;   // max 'd12;
    
reg DisplayOn;

reg VSync;
reg HSync;

reg [7:0] VideoShiftReg;

always @(posedge clock) begin

  if(~reset) begin
    lineCounter   <= 0;
    syncCounter   <= 0;
    MCycleCounter <= 0;
  end

  if (syncCounter != 0 || (MCycleCounter == 'd26 && lineCounter == 0 && TPA && (SC != 0))) begin
    syncCounter <= syncCounter + 1'd1;
  end

  if((TPB || TPA) && syncCounter == 0) begin
    MCycleCounter <= MCycleCounter + 1'd1;
  end

  if(MCycleCounter == 'd28) begin
    lineCounter <= lineCounter + 1'd1;
    MCycleCounter <= 'd0;
  end

  if (syncCounter == 'd12)
    syncCounter <= 'd0;

  if (lineCounter == 'd263)
    lineCounter <= 'd0;

  //Display On flag for controlling the DMA and Interrupt output
  if(Disp_On) 
    DisplayOn <= 1'b1;
  else if (Disp_Off || ~reset)
    DisplayOn <= 1'b0;

  //Flag Logic
  if ((lineCounter == 'd78 || lineCounter == 'd79) && DisplayOn)
    INT <= 1'b0;
  else
    INT <= 1'b1;

  if ((lineCounter >= 'd76 && lineCounter <= 'd79) || (lineCounter >= 'd205 && lineCounter <= 'd207))
    EFx <= 1'b0;
  else 
    EFx <= 1'b1;

end

always @(negedge clock) begin

  //Sync Timing
  CompSync <= ~(HSync ^ VSync);

  //VSync Logic
  if(lineCounter >= 'd16) 
    VSync <= 1'b1;
  else 
    VSync <= 1'b0;

  //HSync Logic
  if (MCycleCounter >= 'd3 | (MCycleCounter == 'd2 && TPA)) 
    HSync <= 1'b1;
  else
    HSync <= 1'b0;

  //DMA Logic
  if(lineCounter >= 'd80 && lineCounter <= 'd207 && ((MCycleCounter == 'd2 && TPA) || MCycleCounter >= 'd3 && MCycleCounter <= 'd19) && DisplayOn)
    DMAO <= 1'b0;
  else 
    DMAO <= 1'b1;

  //Video shift Register
  if(SC == 'd2 && TPB)
    VideoShiftReg <= DataIn;
  else if (~reset) 
    VideoShiftReg <= 'd0;
  else 
    VideoShiftReg <= VideoShiftReg << 1;

  video <= VideoShiftReg[7];

end

endmodule

rtl/rcastudioii.v
//============================================================================
//
//  This program is free software; you can redistribute it and/or modify it
//  under the terms of the GNU General Public License as published by the Free
//  Software Foundation; either version 2 of the License, or (at your option)
//  any later version.
//
//  This program is distributed in the hope that it will be useful, but WITHOUT
//  ANY WARRANTY; without even the implied warranty of MERCHANTABILITY or
//  FITNESS FOR A PARTICULAR PURPOSE.  See the GNU General Public License for
//  more details.
//
//  You should have received a copy of the GNU General Public License along
//  with this program; if not, write to the Free Software Foundation, Inc.,
//  51 Franklin Street, Fifth Floor, Boston, MA 02110-1301 USA.
//
//============================================================================

module rcastudioii
(
	input         clk,
	input         reset,
	
  input wire        ioctl_download,
  input wire  [7:0] ioctl_index,
  input wire        ioctl_wr,
  input  [24:0] ioctl_addr,
	input   [7:0] ioctl_dout,

	input         pal,
	input         scandouble,

	output reg    ce_pix,

	output reg    HBlank,
	output reg    HSync,
	output reg    VBlank,
	output reg    VSync,

	output  [7:0] video
);


wire        Disp_On;
wire        Disp_Off;
reg         TPA;
reg         TPB;
reg  [1:0]  SC;
reg  [7:0]  DataIn;

reg  [3:0]  EF;

reg   Clear;
reg   INT;
reg   DMAO;
reg   EFx;
reg   CompSync;
wire  Locked;

cdp1861 cdp1861 (
    .clock(clk),
    .reset(reset),
    
    .Disp_On(1'b1),
    .Disp_Off(1'b0),
    .TPA(TPA),
    .TPB(TPB),
    .SC(SC),
    .DataIn(DataIn),

    .Clear(Clear),
    .INT(INT),
    .DMAO(DMAO),
    .EFx(EFx),

    .video(video),
    .CompSync(CompSync),
    .Locked(Locked)
);

reg Q;
reg [7:0] cpu_din;
reg [7:0] cpu_dout;
wire cpu_inp;
wire cpu_out;

reg unsupported;

cdp1802 cdp1802 (
  .clock(clk),
  .resetq(reset),

  .Q(Q),                 // O external pin Q Turns the sound off and on. When logic '1', the beeper is on.
  .EF(EF),              // I 3:0 external flags EF1 to EF4

  .io_din(cpu_din),     
  .io_dout(cpu_dout),    
  .io_n(),              // O 2:0 IO control lines: N2,N1,N0
  .io_inp(cpu_inp),     // O IO input signal
  .io_out(cpu_out),     // O IO output signal

  .unsupported(unsupported),

  .ram_rd(ram_rd),     
  .ram_wr(ram_wr),     
  .ram_a(ram_a),      
  .ram_q(ram_q),      
  .ram_d(ram_d)      
);


wire          ram_rd; // RAM read enable
wire          ram_wr; // RAM write enable
wire  [15:0]  ram_a;  // RAM address
reg    [7:0]  ram_q;  // RAM read data
wire   [7:0]  ram_d;  // RAM write data

wire  [7:0]   romDo_StudioII;
wire  [7:0]   romDo_SingleCart;
wire [11:0]   romA;

rom #(.AW(11), .FN("../rom/studio2.hex")) Rom_StudioII
(
	.clock      (clk            ),
	.ce         (1'b1           ),
	.data_out   (romDo_StudioII ),
	.a          (romA[10:0]     )
);

rom #(.AW(11)) Rom_SingleCart
(
	.clock      (clk            ),
	.ce         (1'b1           ),
	.data_out   (romDo_SingleCart ),
	.a          (romA[10:0]     )
);

bram ram (
  .clk(clk),

  .bram_download(ioctl_download),
  .bram_wr(ioctl_wr),
  .bram_init_address(ioctl_addr),
  .bram_din(ioctl_dout),

  .cs(),
  .addr(),
  .dout()
);

/*
dma dma(
  .clk(clk_sys),
  .rdy(dma_rdy),
  .ctrl(dma_ctrl),
  .src_addr({ dma_src_hi, dma_src_lo }),
  .dst_addr({ dma_dst_hi, dma_dst_lo }),
  .addr(dma_addr), // => to AB
  .din(DI),
  .dout(dma_dout),
  .length(dma_length),
  .busy(dma_busy),
  .sel(dma_sel),
  .write(dma_write)
);
*/

always @(posedge clk) begin
  if(reset) begin
    // 1802
    Q <= 1'b0;

    // 1861
    TPA <= 1'b0;
    TPB <= 1'b0;
    SC <= 2'b00;
    DataIn <= 2'b00;

    // 1861
    Clear <= 1'b1;
    INT <= 1'b1;
    DMAO <= 1'b0;
    EFx <= 1'b0;
  end
  else begin
    Clear <= 1'b0;
    INT <= 1'b0;    
  end

  cpu_din <= ram_q;

end

endmodule

verilator/sim.v
`timescale 1ns/1ns
// top end ff for verilator

module top(

   input clk_48 /*verilator public_flat*/,
   input clk_24 /*verilator public_flat*/,
   input reset/*verilator public_flat*/,
   input [11:0]  inputs/*verilator public_flat*/,

   output [7:0] VGA_R/*verilator public_flat*/,
   output [7:0] VGA_G/*verilator public_flat*/,
   output [7:0] VGA_B/*verilator public_flat*/,
   
   output VGA_HS,
   output VGA_VS,
   output VGA_HB,
   output VGA_VB,

   output [15:0] AUDIO_L,
   output [15:0] AUDIO_R,
   
   input        ioctl_download,
   input        ioctl_upload,
   input        ioctl_wr,
   input [24:0] ioctl_addr,
   input [7:0]  ioctl_dout,
   input [7:0]  ioctl_din,   
   input [7:0]  ioctl_index,
   output  reg  ioctl_wait=1'b0
   
);
   
   // Core inputs/outputs
   wire       pause;
   wire [7:0] audio;
   wire [8:0] rgb;
   wire [3:0] led/*verilator public_flat*/;
   reg [7:0]  trakball/*verilator public_flat*/;
   reg [7:0]  joystick/*verilator public_flat*/;
   reg [9:0]  playerinput/*verilator public_flat*/;  

   // Hardcode default switches
   reg [7:0]  sw1 = { 1'b0, 1'b0,2'b0,2'b0,2'b0 };
   reg [7:0]  sw2 = 8'h02;

   // Convert 3bpp output to 8bpp
   assign VGA_R = {rgb[2:0],rgb[2:0],rgb[2:1]};
   assign VGA_G = {rgb[5:3],rgb[5:3],rgb[5:4]};
   assign VGA_B = {rgb[8:6],rgb[8:6],rgb[8:7]};
    
   // MAP INPUTS FROM SIM
   // -------------------
   assign playerinput[9] = ~inputs[10]; // coin r
   assign playerinput[8] = ~inputs[9]; // coin m
   assign playerinput[7] = ~inputs[8]; // coin l
   assign playerinput[6] = 1'b1;       // self-test
   assign playerinput[5] = 1'b0;       // cocktail
   assign playerinput[4] = 1'b1;       // slam
   assign playerinput[3] = ~inputs[7]; // start 2
   assign playerinput[2] = ~inputs[6]; // start 1
   assign playerinput[1] = ~inputs[5]; // fire 2
   assign playerinput[0] = ~inputs[4]; // fire 1  
   assign joystick[7:4] = { ~inputs[0],~inputs[1],~inputs[2],~inputs[3] }; // right, left, down, up 1
   assign joystick[3:0] = { ~inputs[0],~inputs[1],~inputs[2],~inputs[3] }; // right, left, down, up 2
   assign pause = inputs[11];       // pause

   // MAP OUTPUTS
   assign AUDIO_L = {audio,audio};
   assign AUDIO_R = AUDIO_L;

   reg ce_pix;
   
   always @(posedge clk_48) begin
      reg old_clk;
      
      old_clk <= clk_48;
      ce_pix <= old_clk & ~clk_48;

      //$display("reset %x clk_48 %x clk_24 %x", reset, clk_48, clk_24); 
   end

rcastudioii rcastudio
(
	.clk(clk_48),
	.reset(reset),
	
   //ioctl
	.ioctl_download(ioctl_download),
	.ioctl_index(ioctl_index),
	.ioctl_wr(ioctl_wr),
	.ioctl_addr(ioctl_addr),
	.ioctl_dout(ioctl_dout),

	.pal(1'b1),
	.scandouble(forced_scandoubler),

	.ce_pix(ce_pix),

	.HBlank(HBlank),
	.HSync(HSync),
	.VBlank(VBlank),
	.VSync(VSync),

	.video(video)
);


endmodule

verilator/sim.vcd
$version Generated by VerilatedVcd $end
$date Fri Jun 17 16:34:40 2022 $end
$timescale 1s $end

 $scope module TOP $end
  $var wire 16 . AUDIO_L [15:0] $end
  $var wire 16 / AUDIO_R [15:0] $end
  $var wire  8 ) VGA_B [7:0] $end
  $var wire  8 ( VGA_G [7:0] $end
  $var wire  1 , VGA_HB $end
  $var wire  1 * VGA_HS $end
  $var wire  8 ' VGA_R [7:0] $end
  $var wire  1 - VGA_VB $end
  $var wire  1 + VGA_VS $end
  $var wire  1 $ clk_24 $end
  $var wire  1 # clk_48 $end
  $var wire 12 & inputs [11:0] $end
  $var wire 25 3 ioctl_addr [24:0] $end
  $var wire  8 5 ioctl_din [7:0] $end
  $var wire  8 4 ioctl_dout [7:0] $end
  $var wire  1 0 ioctl_download $end
  $var wire  8 6 ioctl_index [7:0] $end
  $var wire  1 1 ioctl_upload $end
  $var wire  1 7 ioctl_wait $end
  $var wire  1 2 ioctl_wr $end
  $var wire  1 % reset $end
  $scope module top $end
   $var wire 16 C AUDIO_L [15:0] $end
   $var wire 16 D AUDIO_R [15:0] $end
   $var wire  8 > VGA_B [7:0] $end
   $var wire  8 = VGA_G [7:0] $end
   $var wire  1 A VGA_HB $end
   $var wire  1 ? VGA_HS $end
   $var wire  8 < VGA_R [7:0] $end
   $var wire  1 B VGA_VB $end
   $var wire  1 @ VGA_VS $end
   $var wire  8 N audio [7:0] $end
   $var wire  1 V ce_pix $end
   $var wire  1 9 clk_24 $end
   $var wire  1 8 clk_48 $end
   $var wire 12 ; inputs [11:0] $end
   $var wire 25 H ioctl_addr [24:0] $end
   $var wire  8 J ioctl_din [7:0] $end
   $var wire  8 I ioctl_dout [7:0] $end
   $var wire  1 E ioctl_download $end
   $var wire  8 K ioctl_index [7:0] $end
   $var wire  1 F ioctl_upload $end
   $var wire  1 L ioctl_wait $end
   $var wire  1 G ioctl_wr $end
   $var wire  8 R joystick [7:0] $end
   $var wire  4 P led [3:0] $end
   $var wire  1 M pause $end
   $var wire 10 S playerinput [9:0] $end
   $var wire  1 : reset $end
   $var wire  9 O rgb [8:0] $end
   $var wire  8 T sw1 [7:0] $end
   $var wire  8 U sw2 [7:0] $end
   $var wire  8 Q trakball [7:0] $end
   $scope module unnamedblk1 $end
    $var wire  1 W old_clk $end
   $upscope $end
  $upscope $end
 $upscope $end
$enddefinitions $end


#0
1#
0$
1%
b000000000000 &
b00000000 '
b00000000 (
b00000000 )
0*
0+
0,
0-
b0000000000000000 .
b0000000000000000 /
10
01
12
b1111111111111111111111111 3
b00000000 4
b00000000 5
b00000000 6
07
18
09
1:
b000000000000 ;
b00000000 <
b00000000 =
b00000000 >
0?
0@
0A
0B
b0000000000000000 C
b0000000000000000 D
1E
0F
1G
b1111111111111111111111111 H
b00000000 I
b00000000 J
b00000000 K
0L
0M
b00000000 N
b000000000 O
b0000 P
b00000000 Q
b11111111 R
b1111011111 S
b00000000 T
b00000010 U
0V
0W
#0
0#
b0000000000000000000000000 3
b10010000 4
08
b0000000000000000000000000 H
b10010000 I
#0
1#
1$
18
19
1W
#1
0#
0$
b0000000000000000000000001 3
b10110001 4
08
09
b0000000000000000000000001 H
b10110001 I
#2
b0000000000000000000000011 3
b10100101 4
b0000000000000000000000011 H
b10100101 I
#3
b0000000000000000000000101 3
b11111000 4
b0000000000000000000000101 H
b11111000 I
#4
b0000000000000000000000111 3
b10110010 4
b0000000000000000000000111 H
b10110010 I
#5
b0000000000000000000001001 3
b10111000 4
b0000000000000000000001001 H
b10111000 I
#6
b0000000000000000000001011 3
b00011100 4
b0000000000000000000001011 H
b00011100 I
#7
b0000000000000000000001101 3
b11111000 4
b0000000000000000000001101 H
b11111000 I
#8
b0000000000000000000001111 3
b10100010 4
b0000000000000000000001111 H
b10100010 I
#9
b0000000000000000000010001 3
b01101011 4
b0000000000000000000010001 H
b01101011 I
#10
b0000000000000000000010011 3
b11111000 4
b0000000000000000000010011 H
b11111000 I
#11
b0000000000000000000010101 3
b10110101 4
b0000000000000000000010101 H
b10110101 I
#12
b0000000000000000000010111 3
b01111010 4
b0000000000000000000010111 H
b01111010 I
#13
b0000000000000000000011001 3
b11110110 4
b0000000000000000000011001 H
b11110110 I
#14
b0000000000000000000011011 3
b01110000 4
b0000000000000000000011011 H
b01110000 I
#15
b0000000000000000000011101 3
b01111000 4
b0000000000000000000011101 H
b01111000 I
#16
b0000000000000000000011111 3
b01110011 4
b0000000000000000000011111 H
b01110011 I
#17
b0000000000000000000100001 3
b00000000 4
b0000000000000000000100001 H
b00000000 I
#18
b0000000000000000000100011 3
b01111110 4
b0000000000000000000100011 H
b01111110 I
#19
b0000000000000000000100101 3
b00011001 4
b0000000000000000000100101 H
b00011001 I
#20
b0000000000000000000100111 3
b00001001 4
b0000000000000000000100111 H
b00001001 I
#21
b0000000000000000000101001 3
b11111000 4
b0000000000000000000101001 H
b11111000 I
#22
b0000000000000000000101011 3
b10101000 4
b0000000000000000000101011 H
b10101000 I
#23
b0000000000000000000101101 3
b10100000 4
b0000000000000000000101101 H
b10100000 I
#24
b0000000000000000000101111 3
b00100000 4
b0000000000000000000101111 H
b00100000 I
#25
b0000000000000000000110001 3
b11100010 4
b0000000000000000000110001 H
b11100010 I
#26
b0000000000000000000110011 3
b10100000 4
b0000000000000000000110011 H
b10100000 I
#27
b0000000000000000000110101 3
b00100000 4
b0000000000000000000110101 H
b00100000 I
#28
b0000000000000000000110111 3
b10000000 4
b0000000000000000000110111 H
b10000000 I
#29
b0000000000000000000111001 3
b10100000 4
b0000000000000000000111001 H
b10100000 I
#30
b0000000000000000000111011 3
b00101111 4
b0000000000000000000111011 H
b00101111 I
#31
b0000000000000000000111101 3
b10100000 4
b0000000000000000000111101 H
b10100000 I
#32
b0000000000000000000111111 3
b00111100 4
b0000000000000000000111111 H
b00111100 I
#33
b0000000000000000001000001 3
b00001000 4
b0000000000000000001000001 H
b00001000 I
#34
b0000000000000000001000011 3
b01000111 4
b0000000000000000001000011 H
b01000111 I
#35
b0000000000000000001000101 3
b00000001 4
b0000000000000000001000101 H
b00000001 I
#36
b0000000000000000001000111 3
b10001000 4
b0000000000000000001000111 H
b10001000 I
#37
b0000000000000000001001001 3
b11001101 4
b0000000000000000001001001 H
b11001101 I
#38
b0000000000000000001001011 3
b01000000 4
b0000000000000000001001011 H
b01000000 I
#39
b0000000000000000001001101 3
b00110010 4
b0000000000000000001001101 H
b00110010 I
#40
b0000000000000000001001111 3
b01111011 4
b0000000000000000001001111 H
b01111011 I
#41
b0000000000000000001010001 3
b00011000 4
b0000000000000000001010001 H
b00011000 I
#42
b0000000000000000001010011 3
b10001001 4
b0000000000000000001010011 H
b10001001 I
#43
b0000000000000000001010101 3
b10010011 4
b0000000000000000001010101 H
b10010011 I
#44
b0000000000000000001010111 3
b10011001 4
b0000000000000000001010111 H
b10011001 I
#45
b0000000000000000001011001 3
b11110100 4
b0000000000000000001011001 H
b11110100 I
#46
b0000000000000000001011011 3
b11110110 4
b0000000000000000001011011 H
b11110110 I
#47
b0000000000000000001011101 3
b11110100 4
b0000000000000000001011101 H
b11110100 I
#48
0%
b0000000000000000001011111 3
b01010110 4
0:
b0000000000000000001011111 H
b01010110 I
#49
b0000000000000000001100001 3
b11110010 4
b0000000000000000001100001 H
b11110010 I
#50
b0000000000000000001100011 3
b11010100 4
b0000000000000000001100011 H
b11010100 I
#51
b0000000000000000001100101 3
b00000000 4
b0000000000000000001100101 H
b00000000 I
#52
b0000000000000000001100111 3
b00100010 4
b0000000000000000001100111 H
b00100010 I
#53
b0000000000000000001101001 3
b00010010 4
b0000000000000000001101001 H
b00010010 I
#54
b0000000000000000001101011 3
b10010110 4
b0000000000000000001101011 H
b10010110 I
#55
b0000000000000000001101101 3
b10010100 4
b0000000000000000001101101 H
b10010100 I
#56
b0000000000000000001101111 3
b01000101 4
b0000000000000000001101111 H
b01000101 I
#57
b0000000000000000001110001 3
b10101111 4
b0000000000000000001110001 H
b10101111 I
#58
b0000000000000000001110011 3
b11110110 4
b0000000000000000001110011 H
b11110110 I
#59
b0000000000000000001110101 3
b0000000000000000001110101 H
#60
b0000000000000000001110111 3
b10010100 4
b0000000000000000001110111 H
b10010100 I
#61
b0000000000000000001111001 3
b11100000 4
b0000000000000000001111001 H
b11100000 I
#62
b0000000000000000001111011 3
b10001111 4
b0000000000000000001111011 H
b10001111 I
#63
b0000000000000000001111101 3
b00001111 4
b0000000000000000001111101 H
b00001111 I
#64
b0000000000000000001111111 3
b11000000 4
b0000000000000000001111111 H
b11000000 I
#65
b0000000000000000010000001 3
b00000101 4
b0000000000000000010000001 H
b00000101 I
#66
b0000000000000000010000011 3
b11110110 4
b0000000000000000010000011 H
b11110110 I
#67
b0000000000000000010000101 3
b0000000000000000010000101 H
#68
b0000000000000000010000111 3
b11000000 4
b0000000000000000010000111 H
b11000000 I
#69
b0000000000000000010001001 3
b01001100 4
b0000000000000000010001001 H
b01001100 I
#70
b0000000000000000010001011 3
b10001100 4
b0000000000000000010001011 H
b10001100 I
#71
b0000000000000000010001101 3
b00001111 4
b0000000000000000010001101 H
b00001111 I
#72
b0000000000000000010001111 3
b01001100 4
b0000000000000000010001111 H
b01001100 I
#73
b0000000000000000010010001 3
b11010011 4
b0000000000000000010010001 H
b11010011 I
#74
b0000000000000000010010011 3
b01101011 4
b0000000000000000010010011 H
b01101011 I
#75
b0000000000000000010010101 3
b11111010 4
b0000000000000000010010101 H
b11111010 I
